snakeway/__init__.py
snakeway/dto.py
snakeway/recorder.py
snakeway/stats.py
snakeway/webserver.py
snakeway/templates/index.html
snakeway-0.0.4b0.dist-info/METADATA
snakeway-0.0.4b0.dist-info/RECORD
snakeway-0.0.4b0.dist-info/WHEEL
snakeway-0.0.4b0.dist-info/top_level.txt
