Metadata-Version: 2.1
Name: snakeway
Version: 0.0.4b0
Summary: Simple python request profiler
Home-page: UNKNOWN
Author: Piotr Karkut
Author-email: karkucik@gmail.com
License: UNKNOWN
Platform: UNKNOWN
Classifier: Programming Language :: Python :: 3.7
Classifier: License :: OSI Approved :: MIT License
Classifier: Operating System :: OS Independent
Requires-Dist: jinja2
